{
  "type": "thaumaturgy:arcane_crafting_shaped",
  "pattern": [
    "  K",
    " C ",
    "K  "
  ],
  "key": {
    "K": {
      "item": "thaumaturgy:gold_knob"
    },
    "C": {
      "item": "thaumaturgy:greatwood_core"
    }
  },
  "aspects": [
    {
      "aspect": "thaumaturgy:aer",
      "amount": 5
    },
    {
      "aspect": "thaumaturgy:ignis",
      "amount": 5
    },
    {
      "aspect": "thaumaturgy:ordo",
      "amount": 5
    }
  ],
  "result": {
    "item": "thaumaturgy:gold_wand",
    "count": 1,
    "nbt": {
      "vis_storage": {
        "total_capacity": 0,
        "Aspects": [
          { "amount": 0, "aspect": "thaumaturgy:ignis" },
          { "amount": 0, "aspect": "thaumaturgy:terra" },
          { "amount": 0, "aspect": "thaumaturgy:perditio" },
          { "amount": 0, "aspect": "thaumaturgy:aer"},
          { "amount": 0, "aspect": "thaumaturgy:aqua" },
          { "amount": 0, "aspect": "thaumaturgy:ordo" }
        ],
        "max_capacity": 25
      }
    }
  }
}